ausgrid/__init__.py
ausgrid/errors.py
ausgrid_outages-0.0.2.dist-info/LICENSE
ausgrid_outages-0.0.2.dist-info/METADATA
ausgrid_outages-0.0.2.dist-info/WHEEL
ausgrid_outages-0.0.2.dist-info/entry_points.txt
ausgrid_outages-0.0.2.dist-info/top_level.txt
ausgrid_outages-0.0.2.dist-info/RECORD
